multiplication_table/__init__.py
multiplication_table/process_math/Graph.py
multiplication_table/process_math/__init__.py
multiplication_table/process_vis/__init__.py
multiplication_table/process_vis/base_vis.py
multiplication_table/process_vis/edges_vis.py
multiplication_table/process_vis/interface.py
multiplication_table-0.0.1.dist-info/METADATA
multiplication_table-0.0.1.dist-info/WHEEL
multiplication_table-0.0.1.dist-info/top_level.txt
multiplication_table-0.0.1.dist-info/RECORD
