Metadata-Version: 2.1
Name: multiplication-table
Version: 0.0.1
Summary: Visualisation of the modular multiplication table
Home-page: https://github.com/goujilinouhaila-coder/Multiplication_table.git
Author: SOBOLAK Valérian, GOUJILI Nouhaila, SENE Assane, BERRANDOU Assia
Author-email: valerian.sobolak@etu.umontpellier.fr, nouhaila.goujili@etu.umontpellier.fr, assane.sene@etu.umontpellier.fr, assia.berrandou@etu.umontpellier.fr
License: M1 MIND/BIOSTAT
Platform: UNKNOWN
